treport/__init__.py
treport/__main__.py
treport/logger.py
treport/report.py
treport/treport.xsd
treport-0.0.6.dist-info/LICENSE
treport-0.0.6.dist-info/METADATA
treport-0.0.6.dist-info/WHEEL
treport-0.0.6.dist-info/top_level.txt
treport-0.0.6.dist-info/RECORD
