Metadata-Version: 2.1
Name: treport
Version: 0.0.6
Summary: Library for generating tabular reports with results output in MS Excel format
Home-page: https://github.com/novikov-nsa/treport
Author: Sergey Novikov
Author-email: novikov.nsa@yandex.ru
Project-URL: Bug Tracker, https://github.com/novikov-nsa/treport/issues
Classifier: Programming Language :: Python :: 3
Classifier: License :: OSI Approved :: BSD License
Classifier: Operating System :: OS Independent
Requires-Python: >=3.6
License-File: LICENSE
Requires-Dist: lxml (>=4.8.0)
Requires-Dist: Jinja2 (>=3.1.2)
Requires-Dist: openpyxl (>=3.0.10)
Requires-Dist: postgres (>=4.0)
